<links>
	<link>
		<content type="text"><![CDATA[Esta legenda vem de um arquivo XML]]></content>
		<tooltip></tooltip>
		<url>http://link1.com</url>
		<thumbnail>thumbs/video10.jpg</thumbnail>
		<startTime>00:00:00.5</startTime>
		<endTime>00:00:02</endTime>
		<topLeft>
			<x>0</x>
			<y>50</y>
		</topLeft>
		<bottomRight>
			<x>200</x>
			<y>0</y>
		</bottomRight>
	</link>
	<link>
		<content type="text" textColor="0xFF0000" backgroundColor="0x0000FF" ><![CDATA[O <i>formato</i> final ainda não está definido]]></content>
		<tooltip>Esta é a Tooltip 2. E ela é bastante comprida.</tooltip>
		<url>http://link2.com</url>
		<thumbnail>thumbs/video11.jpg</thumbnail>
		<startTime>00:00:02.5</startTime>
		<endTime>00:00:04.00</endTime>
		<topLeft>
			<x>100</x>
			<y>75</y>
		</topLeft>
		<bottomRight>
			<x>300</x>
			<y>25</y>
		</bottomRight>
	</link>
	<link>
		<content type="image">controlbar.png</content>
		<tooltip>Tooltip 3</tooltip>
		<url>http://link3.com</url>
		<startTime>00:00:04.5</startTime>
		<endTime>00:00:06.00</endTime>
		<topLeft>
			<x>20</x>
			<y>20</y>
		</topLeft>
		<bottomRight>
			<x>375</x>
			<y>50</y>
		</bottomRight>
	</link>
</links>
